{"_type":"export","__export_format":4,"__export_date":"2020-06-15T13:15:09.110Z","__export_source":"insomnia.desktop.app:v7.1.1","resources":[{"_id":"req_e41ba6868de047f9b9c5fc516e7dae10","authentication":{},"body":{},"created":1591972494195,"description":"","headers":[],"isPrivate":false,"metaSortKey":-1591874262650,"method":"POST","modified":1591972494195,"name":"Start Test","parameters":[],"parentId":"fld_cf8cd50a24ed4d7c93df3b997ac5ab78","settingDisableRenderRequestBody":false,"settingEncodeUrl":true,"settingFollowRedirects":"global","settingRebuildPath":true,"settingSendCookies":true,"settingStoreCookies":true,"url":"{{ base  }}/api/extensions/v1beta/user/{% response 'body', 'req_f173b02cf00c458891d0c8533f1d28a8', 'b64::JC51aWQ=::46b', 'never' %}/revere-test/start/","_type":"request"},{"_id":"fld_cf8cd50a24ed4d7c93df3b997ac5ab78","created":1591972494192,"description":"","environment":{},"environmentPropertyOrder":null,"metaSortKey":-1591498955432,"modified":1591972503729,"name":"ReVeRe","parentId":"wrk_56bc7b6cea224af29368be23385913b0","_type":"request_group"},{"_id":"wrk_56bc7b6cea224af29368be23385913b0","created":1586083063579,"description":"","modified":1586083063579,"name":"ppserver","parentId":null,"_type":"workspace"},{"_id":"req_15077e98a7014c6097c7cbe871b86d20","authentication":{},"body":{"mimeType":"application/json","text":"{\n\t\"key\": \"user/{% response 'body', 'req_f173b02cf00c458891d0c8533f1d28a8', 'b64::JC51aWQ=::46b', 'never' %}/revere-test/{% response 'body', 'req_e41ba6868de047f9b9c5fc516e7dae10', 'b64::JC5pZA==::46b', 'never' %}/{% response 'body', 'req_e41ba6868de047f9b9c5fc516e7dae10', 'b64::JC53b3JkTGlzdHMuMC5pZA==::46b', 'never' %}.wav\",\n\t\"bucket\": \"{{ bucket  }}\",\n\t\"region\": \"cn\"\n}"},"created":1591972494197,"description":"","headers":[{"id":"pair_b76a462b67304bfa8362a6693e91ba95","name":"Content-Type","value":"application/json"}],"isPrivate":false,"metaSortKey":-1591874262600,"method":"POST","modified":1592214089496,"name":"Process Audio Result","parameters":[],"parentId":"fld_cf8cd50a24ed4d7c93df3b997ac5ab78","settingDisableRenderRequestBody":false,"settingEncodeUrl":true,"settingFollowRedirects":"global","settingRebuildPath":true,"settingSendCookies":true,"settingStoreCookies":true,"url":"{{ base  }}/api/extensions/v1beta/user/{% response 'body', 'req_f173b02cf00c458891d0c8533f1d28a8', 'b64::JC51aWQ=::46b', 'never' %}/revere-test/{% response 'body', 'req_e41ba6868de047f9b9c5fc516e7dae10', 'b64::JC5pZA==::46b', 'never' %}/words/{% response 'body', 'req_e41ba6868de047f9b9c5fc516e7dae10', 'b64::JC53b3JkTGlzdHMuMC5pZA==::46b', 'never' %}/audio/","_type":"request"},{"_id":"req_a98b2ed10b204a698e844e8e4c165d3b","authentication":{},"body":{},"created":1591972494201,"description":"","headers":[],"isPrivate":false,"metaSortKey":-1591874262575,"method":"GET","modified":1592214831501,"name":"Export Test Result","parameters":[],"parentId":"fld_cf8cd50a24ed4d7c93df3b997ac5ab78","settingDisableRenderRequestBody":false,"settingEncodeUrl":true,"settingFollowRedirects":"global","settingRebuildPath":true,"settingSendCookies":true,"settingStoreCookies":true,"url":"{{ base  }}/api/extensions/v1beta/user/{% response 'body', 'req_f173b02cf00c458891d0c8533f1d28a8', 'b64::JC51aWQ=::46b', 'never' %}/revere-test/{% response 'body', 'req_e41ba6868de047f9b9c5fc516e7dae10', 'b64::JC5pZA==::46b', 'never' %}/","_type":"request"},{"_id":"req_ad5a564e32984f5193f1518b0ec74db3","authentication":{},"body":{},"created":1591973683541,"description":"","headers":[],"isPrivate":false,"metaSortKey":-1591874262562.5,"method":"GET","modified":1591973778942,"name":"Retrieve User Tests","parameters":[],"parentId":"fld_cf8cd50a24ed4d7c93df3b997ac5ab78","settingDisableRenderRequestBody":false,"settingEncodeUrl":true,"settingFollowRedirects":"global","settingRebuildPath":true,"settingSendCookies":true,"settingStoreCookies":true,"url":"{{ base  }}/api/extensions/v1beta/user/{% response 'body', 'req_f173b02cf00c458891d0c8533f1d28a8', 'b64::JC51aWQ=::46b', 'never' %}/revere-test/","_type":"request"},{"_id":"req_1baec785846645f98f053f023c4375f7","authentication":{},"body":{},"created":1592214712968,"description":"","headers":[],"isPrivate":false,"metaSortKey":-1591874262556.25,"method":"POST","modified":1592214840502,"name":"Finish test","parameters":[],"parentId":"fld_cf8cd50a24ed4d7c93df3b997ac5ab78","settingDisableRenderRequestBody":false,"settingEncodeUrl":true,"settingFollowRedirects":"global","settingRebuildPath":true,"settingSendCookies":true,"settingStoreCookies":true,"url":"{{ base  }}/api/extensions/v1beta/user/{% response 'body', 'req_f173b02cf00c458891d0c8533f1d28a8', 'b64::JC51aWQ=::46b', 'never' %}/revere-test/{% response 'body', 'req_e41ba6868de047f9b9c5fc516e7dae10', 'b64::JC5pZA==::46b', 'never' %}/finish/","_type":"request"},{"_id":"req_bb045b668038476fa5c2d3692ad81b98","authentication":{"token":"{% response 'body', 'req_d5956d9cf773407f80b7581d11421651', 'b64::JC5hdXRoVG9rZW4=::46b', 'no-history' %}","type":"bearer"},"body":{"mimeType":"multipart/form-data","params":[{"disabled":false,"fileName":"/home/milan/dev/hound/houndify/test_audio/how_many_megabytes_in_a_bit.wav","id":"pair_7011c7eb559b4ad3aec7e03e65b6f01b","name":"file","type":"file","value":""},{"disabled":false,"id":"pair_508be9ed113840348a8f6178b8aadc68","name":"mime","value":"audio/wave"},{"disabled":false,"id":"pair_932489586430465a8bb7b6faeb15dfd3","name":"filename","value":"user/{% response 'body', 'req_f173b02cf00c458891d0c8533f1d28a8', 'b64::JC51aWQ=::46b', 'never' %}/revere-test/{% response 'body', 'req_e41ba6868de047f9b9c5fc516e7dae10', 'b64::JC5pZA==::46b', 'never' %}/{% response 'body', 'req_e41ba6868de047f9b9c5fc516e7dae10', 'b64::JC53b3JkTGlzdHMuMC5pZA==::46b', 'never' %}.wav"}]},"created":1591972494199,"description":"You need to hav","headers":[{"disabled":true,"id":"pair_46ce42998f674d2fb0e4bf6ffc2a35b6","name":"User-Agent","value":"com.medopad.phoenixsdk.Auth-Example-iOS/1.0 iPhone/12.2 hw/sim (GTMSUF/1)"},{"id":"pair_867f6263a4274a59852fc733ae36f244","name":"Content-Type","value":"multipart/form-data"},{"disabled":true,"id":"pair_9d25da2cf3f1446cba3b32d68986b58f","name":"X-Goog-Upload-Command","value":"start"},{"disabled":true,"id":"pair_2bce85c27f094088a484f7f3690ea52b","name":"X-Goog-Upload-Content-Type","value":"image/jpeg"},{"disabled":true,"id":"pair_4a03759e8281495d800c5154ad2f4534","name":"X-Goog-Upload-Protocol","value":"resumable"},{"disabled":true,"id":"pair_8f74a14e21df4d00a4f3db293e1d3dcc","name":"X-Goog-Upload-Content-Length","value":"102796"}],"isPrivate":false,"metaSortKey":-1591874262550,"method":"POST","modified":1592214735870,"name":"Upload Audio to Storage","parameters":[],"parentId":"fld_cf8cd50a24ed4d7c93df3b997ac5ab78","settingDisableRenderRequestBody":false,"settingEncodeUrl":true,"settingFollowRedirects":"global","settingRebuildPath":true,"settingSendCookies":true,"settingStoreCookies":true,"url":"{{ base }}/api/storage/v1beta/upload/{{ bucket  }}","_type":"request"},{"_id":"env_8b1ec03230083df877e71ca87427c6a0ace30876","color":null,"created":1586083063614,"data":{},"dataPropertyOrder":null,"isPrivate":false,"metaSortKey":1586083063614,"modified":1586083063614,"name":"Base Environment","parentId":"wrk_56bc7b6cea224af29368be23385913b0","_type":"environment"},{"_id":"jar_8b1ec03230083df877e71ca87427c6a0ace30876","cookies":[],"created":1586083063616,"modified":1586083063616,"name":"Default Jar","parentId":"wrk_56bc7b6cea224af29368be23385913b0","_type":"cookie_jar"},{"_id":"env_990f95957abb43c58ace5edf9f8c381a","color":null,"created":1586083071435,"data":{"base":"http://localhost:3901","bucket":"ppdeveufrankfurt","clientId":"c1","email":"igor.ivashkovskyi@instandart.com","masterKey":"88888888","phoneNumber":"+380507688541","projectId":"p1","userActivationCode":"05677151","userEmail":"milano.fili+1@gmail.com"},"dataPropertyOrder":{"&":["phoneNumber","email","userEmail","base","masterKey","userActivationCode","projectId","clientId","bucket"]},"isPrivate":false,"metaSortKey":1586083071435,"modified":1591293331311,"name":"localhost - localdev","parentId":"env_8b1ec03230083df877e71ca87427c6a0ace30876","_type":"environment"},{"_id":"env_1c37fc4662e3433e87224fa69f3ecccc","color":null,"created":1587716657874,"data":{"base":"http://localhost:3911","bucket":"testbucket","clientId":"c1","email":"milano.fili@gmail.com","masterKey":"88888888","phoneNumber":"+447484889827","projectId":"p1","userActivationCode":"47710720","userEmail":"milano.fili+1@gmail.com"},"dataPropertyOrder":{"&":["phoneNumber","email","userEmail","base","masterKey","userActivationCode","projectId","clientId","bucket"]},"isPrivate":false,"metaSortKey":1586083420520,"modified":1590149712644,"name":"localhost - docker-compose","parentId":"env_8b1ec03230083df877e71ca87427c6a0ace30876","_type":"environment"},{"_id":"env_37986823e8bd453ba7f949da7e35e350","color":null,"created":1588010912425,"data":{"base":"http://localhost:3901","bucket":"mp-sandbox-do","clientId":"c1","email":"milano.fili@gmail.com","masterKey":"88888888","phoneNumber":"+447484889827","projectId":"p1","userActivationCode":"47710720","userEmail":"milano.fili+1@gmail.com"},"dataPropertyOrder":{"&":["phoneNumber","email","userEmail","base","masterKey","userActivationCode","projectId","clientId","bucket"]},"isPrivate":false,"metaSortKey":1586083245977.5,"modified":1588061663784,"name":"localhost - localdev atlas","parentId":"env_8b1ec03230083df877e71ca87427c6a0ace30876","_type":"environment"},{"_id":"env_e4576ecb8c4f4e7a88cb3c3b5e8c738b","color":null,"created":1588466997201,"data":{"base":"https://devapi.phoenixsvc.io","bucket":"testbucket","clientId":"c1","email":"milano.fili@gmail.com","masterKey":"8888888812312321312321321321312fdsjfdajdsjfadsjfad","phoneNumber":"+447484889827","projectId":"p1","userActivationCode":"47710720","userEmail":"milano.fili+1@gmail.com"},"dataPropertyOrder":{"&":["phoneNumber","email","userEmail","base","masterKey","userActivationCode","projectId","clientId","bucket"]},"isPrivate":false,"metaSortKey":1586083420570,"modified":1588468295908,"name":"localhost - do - phoenixsvc","parentId":"env_8b1ec03230083df877e71ca87427c6a0ace30876","_type":"environment"},{"_id":"env_89b3b8b2d9d241d78c24f78209e3c663","color":null,"created":1589788762929,"data":{"base":"https://devapi.phoenixsvc.io","bucket":"testbucket","clientId":"c1","email":"milano.fili@gmail.com","masterKey":"8888888812312321312321321321312fdsjfdajdsjfadsjfad","phoneNumber":"your_phone","projectId":"p1","userActivationCode":"47710720","userEmail":"your_email"},"dataPropertyOrder":{"&":["phoneNumber","email","userEmail","base","masterKey","userActivationCode","projectId","clientId","bucket"]},"isPrivate":false,"metaSortKey":1586083420595,"modified":1589791394527,"name":"do - phoenixsvc  - empty","parentId":"env_8b1ec03230083df877e71ca87427c6a0ace30876","_type":"environment"},{"_id":"env_426b86f5d890406e9b7072f52e83d397","color":null,"created":1589789218966,"data":{"base":"https://devapi.phoenixsvc.io","bucket":"testbucket","clientId":"c1","email":"milano.fili@gmail.com","masterKey":"8888888812312321312321321321312fdsjfdajdsjfadsjfad","phoneNumber":"+447484889827","projectId":"p1","userActivationCode":"47710720","userEmail":"paresh.masani@huma.com"},"dataPropertyOrder":{"&":["phoneNumber","email","userEmail","base","masterKey","userActivationCode","projectId","clientId","bucket"]},"isPrivate":false,"metaSortKey":1586083420607.5,"modified":1589789250207,"name":"do - phoenixsvc  - paresh","parentId":"env_8b1ec03230083df877e71ca87427c6a0ace30876","_type":"environment"},{"_id":"env_9e8ce81dae0c4edd87522c51fa8da6b7","color":null,"created":1590071179734,"data":{"base":"https://devapi.phoenixsvc.io","bucket":"py-phoenix-server-sandbox-do","clientId":"c1","email":"igor.ivashkovskyi@gmail.com","masterKey":"8888888812312321312321321321312fdsjfdajdsjfadsjfad","phoneNumber":"+380507688541","projectId":"p1","userActivationCode":"47710720","userEmail":"igor.ivashkovskyi@gmail.com"},"dataPropertyOrder":{"&":["phoneNumber","email","userEmail","base","masterKey","userActivationCode","projectId","clientId","bucket"]},"isPrivate":false,"metaSortKey":1586083420601.25,"modified":1590072125723,"name":"do - phoenixsvc  - igor","parentId":"env_8b1ec03230083df877e71ca87427c6a0ace30876","_type":"environment"}]}